basicsr/__init__.py
basicsr/test.py
basicsr/train.py
basicsr/version.py
basicsr/archs/__init__.py
basicsr/archs/arch_util.py
basicsr/archs/dfdnet_arch.py
basicsr/archs/dfdnet_util.py
basicsr/archs/discriminator_arch.py
basicsr/archs/duf_arch.py
basicsr/archs/edsr_arch.py
basicsr/archs/edvr_arch.py
basicsr/archs/inception.py
basicsr/archs/rcan_arch.py
basicsr/archs/ridnet_arch.py
basicsr/archs/rrdbnet_arch.py
basicsr/archs/spynet_arch.py
basicsr/archs/srresnet_arch.py
basicsr/archs/stylegan2_arch.py
basicsr/archs/tof_arch.py
basicsr/archs/vgg_arch.py
basicsr/data/__init__.py
basicsr/data/data_sampler.py
basicsr/data/data_util.py
basicsr/data/degradations.py
basicsr/data/ffhq_dataset.py
basicsr/data/paired_image_dataset.py
basicsr/data/prefetch_dataloader.py
basicsr/data/reds_dataset.py
basicsr/data/single_image_dataset.py
basicsr/data/transforms.py
basicsr/data/video_test_dataset.py
basicsr/data/vimeo90k_dataset.py
basicsr/losses/__init__.py
basicsr/losses/loss_util.py
basicsr/losses/losses.py
basicsr/metrics/__init__.py
basicsr/metrics/fid.py
basicsr/metrics/metric_util.py
basicsr/metrics/niqe.py
basicsr/metrics/psnr_ssim.py
basicsr/models/__init__.py
basicsr/models/base_model.py
basicsr/models/edvr_model.py
basicsr/models/esrgan_model.py
basicsr/models/lr_scheduler.py
basicsr/models/sr_model.py
basicsr/models/srgan_model.py
basicsr/models/stylegan2_model.py
basicsr/models/video_base_model.py
basicsr/models/video_gan_model.py
basicsr/ops/__init__.py
basicsr/ops/dcn/__init__.py
basicsr/ops/dcn/deform_conv.py
basicsr/ops/dcn/src/deform_conv_cuda.cpp
basicsr/ops/dcn/src/deform_conv_cuda_kernel.cu
basicsr/ops/dcn/src/deform_conv_ext.cpp
basicsr/ops/fused_act/__init__.py
basicsr/ops/fused_act/fused_act.py
basicsr/ops/fused_act/src/fused_bias_act.cpp
basicsr/ops/fused_act/src/fused_bias_act_kernel.cu
basicsr/ops/upfirdn2d/__init__.py
basicsr/ops/upfirdn2d/upfirdn2d.py
basicsr/ops/upfirdn2d/src/upfirdn2d.cpp
basicsr/ops/upfirdn2d/src/upfirdn2d_kernel.cu
basicsr-1.3.3.3.dist-info/METADATA
basicsr-1.3.3.3.dist-info/WHEEL
basicsr-1.3.3.3.dist-info/top_level.txt
basicsr-1.3.3.3.dist-info/RECORD
