Metadata-Version: 2.1
Name: basicsr
Version: 1.3.3.3
Summary: Open Source Image and Video Super-Resolution Toolbox
Home-page: https://github.com/xinntao/BasicSR
Author: Xintao Wang
Author-email: xintao.wang@outlook.com
License: Apache License 2.0
Keywords: computer vision,restoration,super resolution
Platform: UNKNOWN
Classifier: Development Status :: 4 - Beta
Classifier: License :: OSI Approved :: Apache Software License
Classifier: Operating System :: OS Independent
Classifier: Programming Language :: Python :: 3
Classifier: Programming Language :: Python :: 3.7
Classifier: Programming Language :: Python :: 3.8
Requires-Dist: addict
Requires-Dist: future
Requires-Dist: lmdb
Requires-Dist: numpy
Requires-Dist: opencv-python
Requires-Dist: Pillow
Requires-Dist: pyyaml
Requires-Dist: requests
Requires-Dist: scikit-image
Requires-Dist: scipy
Requires-Dist: tb-nightly
Requires-Dist: torch (>=1.7)
Requires-Dist: torchvision
Requires-Dist: tqdm
Requires-Dist: yapf
